lektor_fixedlang.py
lektor_fixedlang-0.5.dist-info/LICENSE.txt
lektor_fixedlang-0.5.dist-info/METADATA
lektor_fixedlang-0.5.dist-info/WHEEL
lektor_fixedlang-0.5.dist-info/entry_points.txt
lektor_fixedlang-0.5.dist-info/top_level.txt
lektor_fixedlang-0.5.dist-info/RECORD
