Metadata-Version: 2.1
Name: lektor-fixedlang
Version: 0.5
Summary: Set fixed languages for patterns in Lektor.
Author-email: "H. Turgut Uyar" <uyar@tekir.org>
License: Copyright 2024 H. Turgut Uyar <uyar@tekir.org>
Project-URL: repository, https://github.com/uyar/lektor-fixedlang
Keywords: lektor,plugin
Classifier: Development Status :: 4 - Beta
Classifier: Environment :: Plugins
Classifier: Framework :: Lektor
Classifier: Intended Audience :: Developers
Classifier: License :: OSI Approved :: BSD License
Classifier: Programming Language :: Python
Classifier: Programming Language :: Python :: 3.8
Classifier: Programming Language :: Python :: 3.9
Classifier: Programming Language :: Python :: 3.10
Classifier: Programming Language :: Python :: 3.11
Classifier: Programming Language :: Python :: 3.12
Classifier: Topic :: Internet :: WWW/HTTP :: Site Management
Requires-Python: ~=3.8
License-File: LICENSE.txt
Requires-Dist: lektor
Requires-Dist: lxml
Provides-Extra: dev
Requires-Dist: lektor-fixedlang[style,tests] ; extra == 'dev'
Requires-Dist: build ; extra == 'dev'
Requires-Dist: twine ; extra == 'dev'
Requires-Dist: tox ; extra == 'dev'
Provides-Extra: style
Requires-Dist: ruff ; extra == 'style'
Provides-Extra: tests
Requires-Dist: pytest ; extra == 'tests'
Requires-Dist: pytest-cov ; extra == 'tests'
